bahamut_ani_stat/__init__.py
bahamut_ani_stat/__main__.py
bahamut_ani_stat/settings.py
bahamut_ani_stat/cli/__init__.py
bahamut_ani_stat/cli/db_commands.py
bahamut_ani_stat/cli/options.py
bahamut_ani_stat/cli/parse_commands.py
bahamut_ani_stat/cli/plot_commands.py
bahamut_ani_stat/db/__init__.py
bahamut_ani_stat/db/models.py
bahamut_ani_stat/db/utils.py
bahamut_ani_stat/parser/__init__.py
bahamut_ani_stat/parser/data_types.py
bahamut_ani_stat/parser/parser.py
bahamut_ani_stat/parser/urls.py
bahamut_ani_stat/plot/__init__.py
bahamut_ani_stat/plot/utils.py
bahamut_ani_stat/plot/static/datatable-anime-filter.js
bahamut_ani_stat/plot/static/dropdown-anime-filter.js
bahamut_ani_stat/plot/static/new-anime-source-update-dropdown.js
bahamut_ani_stat-0.9.0.dist-info/METADATA
bahamut_ani_stat-0.9.0.dist-info/WHEEL
bahamut_ani_stat-0.9.0.dist-info/entry_points.txt
bahamut_ani_stat-0.9.0.dist-info/licenses/LICENSE
bahamut_ani_stat-0.9.0.dist-info/RECORD
