Metadata-Version: 2.4
Name: bahamut_ani_stat
Version: 0.9.0
Summary: Toolkit for Bahamut ani gamer data
Project-URL: Documentation, https://github.com/Lee-W/bahamut_ani_stat/blob/docs/README.md
Project-URL: Repository, https://github.com/Lee-W/bahamut_ani_stat
Project-URL: Issues, https://github.com/Lee-W/bahamut_ani_stat/issues
Project-URL: Changelog, https://github.com/Lee-W/bahamut_ani_stat/blob/main/CHANGELOG.md
Author-email: Wei Lee <weilee.rx@gmail.com>
License: MIT License
License-File: LICENSE
Classifier: Development Status :: 4 - Beta
Classifier: Environment :: Console
Classifier: Intended Audience :: Developers
Classifier: Natural Language :: English
Classifier: Operating System :: OS Independent
Classifier: Programming Language :: Python
Classifier: Programming Language :: Python :: 3
Classifier: Programming Language :: Python :: 3.9
Classifier: Programming Language :: Python :: 3.10
Classifier: Programming Language :: Python :: 3.11
Classifier: Programming Language :: Python :: 3.12
Classifier: Programming Language :: Python :: 3.13
Classifier: Programming Language :: Python :: Implementation :: CPython
Requires-Python: <4.0,>=3.9
Requires-Dist: beautifulsoup4>=4.12.3
Requires-Dist: bokeh>=3.0.0
Requires-Dist: click>=8.0.1
Requires-Dist: dataclasses-json>=0.5.4
Requires-Dist: httpx>=0.27.0
Requires-Dist: lxml>=5.0.0
Requires-Dist: pandas>=2.0.0
Requires-Dist: pydantic-settings>=2.4.0
Requires-Dist: pydantic>=2.0.0
Requires-Dist: setuptools<76.0,>=72.1
Requires-Dist: sqlalchemy[mypy]<2.0.0,>=1.4.0
Requires-Dist: tqdm>=4.61.1
